pydoge_api/__init__.py
pydoge_api/_version.py
pydoge_api/analytic.py
pydoge_api/api.py
pydoge_api/client.py
pydoge_api/config.py
pydoge_api/endpoints/__init__.py
pydoge_api/endpoints/payments.py
pydoge_api/endpoints/savings.py
pydoge_api/models/__init__.py
pydoge_api/models/payments.py
pydoge_api/models/savings.py
pydoge_api/utils/__init__.py
pydoge_api/utils/async_tools.py
pydoge_api/utils/exporter.py
pydoge_api/utils/pagination.py
pydoge_api-0.2.1.dist-info/licenses/LICENSE
pydoge_api-0.2.1.dist-info/METADATA
pydoge_api-0.2.1.dist-info/WHEEL
pydoge_api-0.2.1.dist-info/top_level.txt
pydoge_api-0.2.1.dist-info/RECORD
