Metadata-Version: 2.4
Name: pydoge_api
Version: 0.2.1
Summary: PyDOGE API is an advanced, Python wrapper for interacting with the public-facing API of the Department of Government Efficiency (DOGE)
Author-email: "Hassan, Muhammad" <blazebyte2@gmail.com>
License-Expression: MIT
Project-URL: Homepage, https://github.com/ihassan8/pydoge-api
Project-URL: Documentation, https://github.com/ihassan8/pydoge-api
Project-URL: Issues, https://github.com/ihassan8/pydoge-api/issues
Keywords: doge,government efficiency,savings,contracts
Classifier: Intended Audience :: Developers
Classifier: Programming Language :: Python :: 3.9
Classifier: Programming Language :: Python :: 3.10
Classifier: Programming Language :: Python :: 3.11
Classifier: Intended Audience :: Developers
Classifier: Intended Audience :: Information Technology
Classifier: Operating System :: OS Independent
Requires-Python: >=3.9
License-File: LICENSE
Requires-Dist: httpx>=0.26.0
Requires-Dist: pydantic>=2.5.3
Requires-Dist: openpyxl
Dynamic: license-file
